[
  {
    "id": 0,
    "product": "yellow",
    "age": 23,
    "eyeColor": "brown",
    "name": "Joanne Cash",
    "nationality": "italy",
    "origin": "OPTYK",
    "channel": "BOILCAT",
    "email": "joannecash@boilcat.com",
    "phone": "+1 (881) 561-3022",
    "address": "795 Otsego Street, Allison, Massachusetts, 7173",
    "from": "2018-07-05",
    "to": "2018-07-08",
    "nights": 2,
    "country": "Uruguay"
  },
  {
    "id": 1,
    "product": "yellow",
    "age": 23,
    "eyeColor": "blue",
    "name": "Craft Osborn",
    "nationality": "spain",
    "origin": "ZOUNDS",
    "channel": "INDEXIA",
    "email": "craftosborn@indexia.com",
    "phone": "+1 (810) 489-3712",
    "address": "727 Court Square, Foscoe, Maryland, 4381",
    "from": "2018-07-03",
    "to": "2018-07-08",
    "nights": 15,
    "country": "Aruba"
  },
  {
    "id": 2,
    "product": "private",
    "age": 21,
    "eyeColor": "green",
    "name": "Camille Durham",
    "nationality": "italy",
    "origin": "PORTICO",
    "channel": "CALLFLEX",
    "email": "camilledurham@callflex.com",
    "phone": "+1 (894) 598-3904",
    "address": "379 Remsen Street, Jamestown, Idaho, 5674",
    "from": "2018-08-04",
    "to": "2018-08-05",
    "nights": 3,
    "country": "Jordan"
  },
  {
    "id": 3,
    "product": "yellow",
    "age": 39,
    "eyeColor": "blue",
    "name": "Carolina Summers",
    "nationality": "italy",
    "origin": "MICRONAUT",
    "channel": "CONFERIA",
    "email": "carolinasummers@conferia.com",
    "phone": "+1 (915) 502-2150",
    "address": "750 Sedgwick Street, Boling, Louisiana, 4955",
    "from": "2018-11-02",
    "to": "2018-11-05",
    "nights": 14,
    "country": "Kyrgyzstan"
  },
  {
    "id": 4,
    "product": "yellow",
    "age": 35,
    "eyeColor": "blue",
    "name": "Bartlett Salinas",
    "nationality": "spain",
    "origin": "ZIGGLES",
    "channel": "DELPHIDE",
    "email": "bartlettsalinas@delphide.com",
    "phone": "+1 (981) 521-2051",
    "address": "346 Bushwick Court, Colton, Marshall Islands, 4041",
    "from": "2018-08-05",
    "to": "2018-08-07",
    "nights": 10,
    "country": "Mayotte"
  },
  {
    "id": 5,
    "product": "beef",
    "age": 20,
    "eyeColor": "green",
    "name": "Lilian Skinner",
    "nationality": "italy",
    "origin": "ZAPHIRE",
    "channel": "DIGIPRINT",
    "email": "lilianskinner@digiprint.com",
    "phone": "+1 (925) 537-2605",
    "address": "923 Cooke Court, Strykersville, Vermont, 7389",
    "from": "2018-07-05",
    "to": "2018-07-011",
    "nights": 11,
    "country": "Albania"
  }
]
